{
  "concepts": [
    { "name": "d3.js", "weight": 0.9, "sentiment": 0.5 },
    { "name": "visualization", "weight": 0.8, "sentiment": 0.3 },
    { "name": "force-directed graph", "weight": 0.95, "sentiment": 0.6 },
    { "name": "html", "weight": 0.5, "sentiment": 0.1 },
    { "name": "css", "weight": 0.4, "sentiment": 0.1 },
    { "name": "node.js", "weight": 0.7, "sentiment": 0.4 },
    { "name": "cognitive weaver", "weight": 1.0, "sentiment": 0.8 },
    { "name": "data persistence", "weight": 0.85, "sentiment": 0.2 },
    { "name": "mnemonic codec", "weight": 1.0, "sentiment": 0.9 }
  ],
  "relationships": [
    { "source": "d3.js", "target": "visualization", "weight": 0.9 },
    { "source": "d3.js", "target": "force-directed graph", "weight": 0.8 },
    { "source": "visualization", "target": "html", "weight": 0.6 },
    { "source": "html", "target": "css", "weight": 0.7 },
    { "source": "node.js", "target": "cognitive weaver", "weight": 0.9 },
    { "source": "cognitive weaver", "target": "d3.js", "weight": 1.0 },
    { "source": "mnemonic codec", "target": "data persistence", "weight": 1.0 },
    { "source": "node.js", "target": "mnemonic codec", "weight": 0.6 }
  ]
}